{
  "name": "BSLimbIKModifier",
  "version": 0,
  "signature": "0x8ea971e5",
  "size_x86": 76,
  "size_x86_64": 120,
  "parent": "hkbModifier",
  "vtable": true,
  "members": [
    {
      "name": "limitAngleDegrees",
      "offset_x86": 44,
      "offset_x86_64": 80,
      "ctype": "hkReal",
      "vtype": "TYPE_REAL",
      "vsubtype": "TYPE_VOID",
      "arrsize": 0,
      "flags": "FLAGS_NONE",
      "default": 0
    },
    {
      "name": "currentAngle",
      "offset_x86": 48,
      "offset_x86_64": 84,
      "ctype": "hkReal",
      "vtype": "TYPE_REAL",
      "vsubtype": "TYPE_VOID",
      "arrsize": 0,
      "flags": "FLAGS_NONE|SERIALIZE_IGNORED",
      "default": 0
    },
    {
      "name": "startBoneIndex",
      "offset_x86": 52,
      "offset_x86_64": 88,
      "ctype": "hkInt16",
      "vtype": "TYPE_INT16",
      "vsubtype": "TYPE_VOID",
      "arrsize": 0,
      "flags": "FLAGS_NONE",
      "default": 0
    },
    {
      "name": "endBoneIndex",
      "offset_x86": 54,
      "offset_x86_64": 90,
      "ctype": "hkInt16",
      "vtype": "TYPE_INT16",
      "vsubtype": "TYPE_VOID",
      "arrsize": 0,
      "flags": "FLAGS_NONE",
      "default": 0
    },
    {
      "name": "gain",
      "offset_x86": 56,
      "offset_x86_64": 92,
      "ctype": "hkReal",
      "vtype": "TYPE_REAL",
      "vsubtype": "TYPE_VOID",
      "arrsize": 0,
      "flags": "FLAGS_NONE",
      "default": 0
    },
    {
      "name": "boneRadius",
      "offset_x86": 60,
      "offset_x86_64": 96,
      "ctype": "hkReal",
      "vtype": "TYPE_REAL",
      "vsubtype": "TYPE_VOID",
      "arrsize": 0,
      "flags": "FLAGS_NONE",
      "default": 0
    },
    {
      "name": "castOffset",
      "offset_x86": 64,
      "offset_x86_64": 100,
      "ctype": "hkReal",
      "vtype": "TYPE_REAL",
      "vsubtype": "TYPE_VOID",
      "arrsize": 0,
      "flags": "FLAGS_NONE",
      "default": 0
    },
    {
      "name": "timeStep",
      "offset_x86": 68,
      "offset_x86_64": 104,
      "ctype": "hkReal",
      "vtype": "TYPE_REAL",
      "vsubtype": "TYPE_VOID",
      "arrsize": 0,
      "flags": "FLAGS_NONE|SERIALIZE_IGNORED",
      "default": 0
    },
    {
      "name": "pSkeletonMemory",
      "offset_x86": 72,
      "offset_x86_64": 112,
      "ctype": "void*",
      "vtype": "TYPE_POINTER",
      "vsubtype": "TYPE_VOID",
      "arrsize": 0,
      "flags": "FLAGS_NONE|SERIALIZE_IGNORED",
      "default": 0
    }
  ]
}