{
  "name": "hkpHingeConstraintDataAtoms",
  "version": 1,
  "signature": "0x6958371c",
  "size_x86": 192,
  "size_x86_64": 192,
  "parent_has_string": false,
  "vtable": false,
  "has_string": false,
  "enums": [
    {
      "name": "Axis",
      "vtype": "TYPE_ENUM",
      "vsubtype": "TYPE_VOID",
      "flags": "00000000",
      "enum_item": [
        {
          "name": "AXIS_AXLE",
          "value": 0
        }
      ]
    }
  ],
  "members": [
    {
      "name": "transforms",
      "class_ref": "hkpSetLocalTransformsConstraintAtom",
      "has_string": false,
      "ctype": "struct hkpSetLocalTransformsConstraintAtom",
      "vtype": "TYPE_STRUCT",
      "vsubtype": "TYPE_VOID",
      "offset_x86": 0,
      "offset_x86_64": 0,
      "type_size_x86": 144,
      "type_size_x86_64": 144,
      "arrsize": 0,
      "flags": "FLAGS_NONE",
      "default": 0
    },
    {
      "name": "setupStabilization",
      "class_ref": "hkpSetupStabilizationAtom",
      "has_string": false,
      "ctype": "struct hkpSetupStabilizationAtom",
      "vtype": "TYPE_STRUCT",
      "vsubtype": "TYPE_VOID",
      "offset_x86": 144,
      "offset_x86_64": 144,
      "type_size_x86": 16,
      "type_size_x86_64": 16,
      "arrsize": 0,
      "flags": "FLAGS_NONE",
      "default": 0
    },
    {
      "name": "2dAng",
      "class_ref": "hkp2dAngConstraintAtom",
      "has_string": false,
      "ctype": "struct hkp2dAngConstraintAtom",
      "vtype": "TYPE_STRUCT",
      "vsubtype": "TYPE_VOID",
      "offset_x86": 160,
      "offset_x86_64": 160,
      "type_size_x86": 4,
      "type_size_x86_64": 4,
      "arrsize": 0,
      "flags": "FLAGS_NONE",
      "default": 0
    },
    {
      "name": "ballSocket",
      "class_ref": "hkpBallSocketConstraintAtom",
      "has_string": false,
      "ctype": "struct hkpBallSocketConstraintAtom",
      "vtype": "TYPE_STRUCT",
      "vsubtype": "TYPE_VOID",
      "offset_x86": 164,
      "offset_x86_64": 164,
      "type_size_x86": 16,
      "type_size_x86_64": 16,
      "arrsize": 0,
      "flags": "FLAGS_NONE",
      "default": 0
    }
  ]
}