{
  "name": "hkpSimpleMeshShape",
  "version": 0,
  "signature": "0x16b3c811",
  "size_x86": 68,
  "size_x86_64": 104,
  "parent": "hkpShapeCollection",
  "parent_has_string": false,
  "vtable": true,
  "has_string": false,
  "members": [
    {
      "name": "vertices",
      "has_string": false,
      "ctype": "hkArray<hkVector4>",
      "vtype": "TYPE_ARRAY",
      "vsubtype": "TYPE_VECTOR4",
      "offset_x86": 24,
      "offset_x86_64": 48,
      "type_size_x86": 12,
      "type_size_x86_64": 16,
      "arrsize": 0,
      "flags": "FLAGS_NONE",
      "default": 0
    },
    {
      "name": "triangles",
      "class_ref": "hkpSimpleMeshShapeTriangle",
      "has_string": false,
      "ctype": "hkArray<struct hkpSimpleMeshShapeTriangle>",
      "vtype": "TYPE_ARRAY",
      "vsubtype": "TYPE_STRUCT",
      "offset_x86": 36,
      "offset_x86_64": 64,
      "type_size_x86": 12,
      "type_size_x86_64": 16,
      "arrsize": 0,
      "flags": "FLAGS_NONE",
      "default": 0
    },
    {
      "name": "materialIndices",
      "has_string": false,
      "ctype": "hkArray<hkUint8>",
      "vtype": "TYPE_ARRAY",
      "vsubtype": "TYPE_UINT8",
      "offset_x86": 48,
      "offset_x86_64": 80,
      "type_size_x86": 12,
      "type_size_x86_64": 16,
      "arrsize": 0,
      "flags": "FLAGS_NONE",
      "default": 0
    },
    {
      "name": "radius",
      "has_string": false,
      "ctype": "hkReal",
      "vtype": "TYPE_REAL",
      "vsubtype": "TYPE_VOID",
      "offset_x86": 60,
      "offset_x86_64": 96,
      "type_size_x86": 4,
      "type_size_x86_64": 4,
      "arrsize": 0,
      "flags": "FLAGS_NONE",
      "default": 0
    },
    {
      "name": "weldingType",
      "enum_ref": "WeldingType",
      "has_string": false,
      "ctype": "enum WeldingType",
      "vtype": "TYPE_ENUM",
      "vsubtype": "TYPE_UINT8",
      "offset_x86": 64,
      "offset_x86_64": 100,
      "type_size_x86": 1,
      "type_size_x86_64": 1,
      "arrsize": 0,
      "flags": "FLAGS_NONE",
      "default": 6
    }
  ]
}