{
  "name": "hkxVertexBufferVertexData",
  "version": 0,
  "signature": "0xd72b6fd0",
  "size_x86": 84,
  "size_x86_64": 104,
  "vtable": false,
  "members": [
    {
      "name": "vectorData",
      "offset_x86": 0,
      "offset_x86_64": 0,
      "ctype": "hkArray<hkVector4>",
      "vtype": "TYPE_ARRAY",
      "vsubtype": "TYPE_VECTOR4",
      "arrsize": 0,
      "flags": "FLAGS_NONE",
      "default": 0
    },
    {
      "name": "floatData",
      "offset_x86": 12,
      "offset_x86_64": 16,
      "ctype": "hkArray<hkReal>",
      "vtype": "TYPE_ARRAY",
      "vsubtype": "TYPE_REAL",
      "arrsize": 0,
      "flags": "FLAGS_NONE",
      "default": 0
    },
    {
      "name": "uint32Data",
      "offset_x86": 24,
      "offset_x86_64": 32,
      "ctype": "hkArray<hkUint32>",
      "vtype": "TYPE_ARRAY",
      "vsubtype": "TYPE_UINT32",
      "arrsize": 0,
      "flags": "FLAGS_NONE",
      "default": 0
    },
    {
      "name": "uint16Data",
      "offset_x86": 36,
      "offset_x86_64": 48,
      "ctype": "hkArray<hkUint16>",
      "vtype": "TYPE_ARRAY",
      "vsubtype": "TYPE_UINT16",
      "arrsize": 0,
      "flags": "FLAGS_NONE",
      "default": 0
    },
    {
      "name": "uint8Data",
      "offset_x86": 48,
      "offset_x86_64": 64,
      "ctype": "hkArray<hkUint8>",
      "vtype": "TYPE_ARRAY",
      "vsubtype": "TYPE_UINT8",
      "arrsize": 0,
      "flags": "FLAGS_NONE",
      "default": 0
    },
    {
      "name": "numVerts",
      "offset_x86": 60,
      "offset_x86_64": 80,
      "ctype": "hkUint32",
      "vtype": "TYPE_UINT32",
      "vsubtype": "TYPE_VOID",
      "arrsize": 0,
      "flags": "FLAGS_NONE",
      "default": 0
    },
    {
      "name": "vectorStride",
      "offset_x86": 64,
      "offset_x86_64": 84,
      "ctype": "hkUint32",
      "vtype": "TYPE_UINT32",
      "vsubtype": "TYPE_VOID",
      "arrsize": 0,
      "flags": "FLAGS_NONE",
      "default": 0
    },
    {
      "name": "floatStride",
      "offset_x86": 68,
      "offset_x86_64": 88,
      "ctype": "hkUint32",
      "vtype": "TYPE_UINT32",
      "vsubtype": "TYPE_VOID",
      "arrsize": 0,
      "flags": "FLAGS_NONE",
      "default": 0
    },
    {
      "name": "uint32Stride",
      "offset_x86": 72,
      "offset_x86_64": 92,
      "ctype": "hkUint32",
      "vtype": "TYPE_UINT32",
      "vsubtype": "TYPE_VOID",
      "arrsize": 0,
      "flags": "FLAGS_NONE",
      "default": 0
    },
    {
      "name": "uint16Stride",
      "offset_x86": 76,
      "offset_x86_64": 96,
      "ctype": "hkUint32",
      "vtype": "TYPE_UINT32",
      "vsubtype": "TYPE_VOID",
      "arrsize": 0,
      "flags": "FLAGS_NONE",
      "default": 0
    },
    {
      "name": "uint8Stride",
      "offset_x86": 80,
      "offset_x86_64": 100,
      "ctype": "hkUint32",
      "vtype": "TYPE_UINT32",
      "vsubtype": "TYPE_VOID",
      "arrsize": 0,
      "flags": "FLAGS_NONE",
      "default": 0
    }
  ]
}